sap2012/__init__.py
sap2012/SAP_appendices/__init__.py
sap2012/SAP_appendices/internal_gains_appendix_L.py
sap2012/SAP_appendices/solar_gains_appendix_U3.py
sap2012/SAP_tables/U2.py
sap2012/SAP_tables/__init__.py
sap2012/SAP_tables/heating_requirement_table_9c.py
sap2012/SAP_tables/temperature_reduction_when_heating_is_off_table_9b.py
sap2012/SAP_tables/utilisation_factor_for_heating_table_9a.py
sap2012/SAP_tables/utilisation_factor_for_heating_whole_house_table_9a.py
sap2012/SAP_worksheet/CO2_emissions.py
sap2012/SAP_worksheet/SAP_rating.py
sap2012/SAP_worksheet/__init__.py
sap2012/SAP_worksheet/calculate_worksheet.py
sap2012/SAP_worksheet/energy_requirements.py
sap2012/SAP_worksheet/fuel_costs.py
sap2012/SAP_worksheet/heat_losses_and_heat_loss_parameter.py
sap2012/SAP_worksheet/internal_gains.py
sap2012/SAP_worksheet/mean_internal_temperature.py
sap2012/SAP_worksheet/overall_dwelling_dimensions.py
sap2012/SAP_worksheet/solar_gains.py
sap2012/SAP_worksheet/space_heating_requirement.py
sap2012/SAP_worksheet/ventilation_rates.py
sap2012/SAP_worksheet/water_heating_requirement.py
sap2012-0.0.1.dist-info/LICENSE
sap2012-0.0.1.dist-info/METADATA
sap2012-0.0.1.dist-info/WHEEL
sap2012-0.0.1.dist-info/top_level.txt
sap2012-0.0.1.dist-info/RECORD
