Metadata-Version: 2.1
Name: sap2012
Version: 0.0.1
Summary: Python package implementing the SAP2012 domestic building energy calculations
Home-page: https://github.com/building-energy/sap2012
Author: Steven K Firth & Ben Halls
Author-email: s.k.firth@lboro.ac.uk
Classifier: Programming Language :: Python :: 3
Classifier: License :: OSI Approved :: MIT License
Classifier: Operating System :: OS Independent
Requires-Python: >=3.6
License-File: LICENSE
